qsvm/__init__.py
qsvm/__main__.py
qsvm/cli.py
qsvm/core.py
qsvm/exception.py
qsvm/j2helper.py
qsvm/util.py
qsvm-0.2.4.dist-info/licenses/LICENSE
qsvm-0.2.4.dist-info/METADATA
qsvm-0.2.4.dist-info/WHEEL
qsvm-0.2.4.dist-info/entry_points.txt
qsvm-0.2.4.dist-info/top_level.txt
qsvm-0.2.4.dist-info/RECORD
