Metadata-Version: 2.4
Name: qsvm
Version: 0.2.4
Summary: QEMU Systemd virtual machine management tool
Home-page: https://github.com/archmachina/qsvm
Download-URL: https://pypi.org/project/qsvm/
Author: Jesse Reichman
License: MIT
Keywords: QEMU,Systemd,VM,Virtual Machine
License-File: LICENSE
Requires-Dist: obslib<0.3.0,>=0.2.0
Requires-Dist: psutil>=6.1.1
Dynamic: author
Dynamic: description
Dynamic: description-content-type
Dynamic: download-url
Dynamic: home-page
Dynamic: keywords
Dynamic: license
Dynamic: license-file
Dynamic: requires-dist
Dynamic: summary
